{
  "name": "Crackbot",
  "tagline": "Independent Cybersecurity Research Group",
  "description": "Crackbot conducts cybersecurity research, publishes technical analysis, develops security tools and shares actionable threat intelligence to help researchers, defenders and the broader security community.",
  "url": "https://crackbot.in",
  "github": "https://github.com/CrackB0t",
  "contact": "mailto:system@crackbot.in",
  "twitter": "https://x.com/CrackB0t",
  "discord": "https://discord.gg/crackbot"
}